jhvar/__init__.py
jhvar/django/__init__.py
jhvar/django/urls/__init__.py
jhvar/django/urls/middleware/__init__.py
jhvar/django/utils/__init__.py
jhvar_django_utils-0.1.8.dist-info/LICENSE
jhvar_django_utils-0.1.8.dist-info/METADATA
jhvar_django_utils-0.1.8.dist-info/WHEEL
jhvar_django_utils-0.1.8.dist-info/top_level.txt
jhvar_django_utils-0.1.8.dist-info/RECORD
