Metadata-Version: 2.1
Name: jhvar-django-utils
Version: 0.1.8
Summary: A toolkit for django-2.2.5 or higher
Home-page: https://github.com/jhvar/django-utils
Author: jhvar
Author-email: jhvar@outlook.com
License: MIT Licence
Keywords: pip,django,role,util
Platform: UNKNOWN
Classifier: Programming Language :: Python :: 3
Classifier: License :: OSI Approved :: MIT License
Classifier: Operating System :: OS Independent
Requires-Python: >=3.6
Requires-Dist: django (>=2.2.5)
